src/__init__.py
src/homeio-fr.py
homeio_fr-1.0.2.dist-info/METADATA
homeio_fr-1.0.2.dist-info/WHEEL
homeio_fr-1.0.2.dist-info/licenses/LICENSE
homeio_fr-1.0.2.dist-info/RECORD
