Metadata-Version: 2.3
Name: homeio-fr
Version: 1.0.2
Summary: Un module pour intéragir avec Home I/O
Author-email: Gabriel Bourneau <11.gabriel.bourneau@lafase.cl>
License-File: LICENSE
Classifier: Operating System :: OS Independent
Classifier: Programming Language :: Python :: 3
Requires-Python: >=3.8
